canapi/__init__.py
canapi/auth.py
canapi/client.py
canapi/registry/coinbasepro.json
canapi/registry/estimize.json
canapi/registry/iexcloud.json
canapi/registry/polygon.json
canapi-0.0.3.dist-info/LICENSE
canapi-0.0.3.dist-info/METADATA
canapi-0.0.3.dist-info/WHEEL
canapi-0.0.3.dist-info/top_level.txt
canapi-0.0.3.dist-info/RECORD
