Metadata-Version: 2.1
Name: canapi
Version: 0.0.3
Summary: A universal client api generator.
Home-page: https://github.com/finverse/canapi
Author: Matthew Brulhardt
Author-email: mwbrulhardt@finverselabs.com
License: Apache 2.0
Platform: UNKNOWN
Classifier: Programming Language :: Python :: 3
Classifier: Programming Language :: Python :: 3.7
Classifier: Intended Audience :: Developers
Classifier: Intended Audience :: Financial and Insurance Industry
Classifier: Intended Audience :: Science/Research
